odoo/addons/calendar_event_type_color/README.rst
odoo/addons/calendar_event_type_color/__init__.py
odoo/addons/calendar_event_type_color/__manifest__.py
odoo/addons/calendar_event_type_color/i18n/calendar_event_type_color.pot
odoo/addons/calendar_event_type_color/i18n/it.po
odoo/addons/calendar_event_type_color/models/__init__.py
odoo/addons/calendar_event_type_color/models/calendar_event.py
odoo/addons/calendar_event_type_color/readme/CONTRIBUTORS.rst
odoo/addons/calendar_event_type_color/readme/CREDITS.rst
odoo/addons/calendar_event_type_color/readme/DESCRIPTION.rst
odoo/addons/calendar_event_type_color/readme/USAGE.rst
odoo/addons/calendar_event_type_color/static/description/icon.png
odoo/addons/calendar_event_type_color/static/description/index.html
odoo/addons/calendar_event_type_color/static/src/views/attendee_calendar/attendee_calendar_model.esm.js
odoo/addons/calendar_event_type_color/views/calendar_event_type_views.xml
odoo/addons/calendar_event_type_color/views/calendar_event_views.xml
odoo_addon_calendar_event_type_color-16.0.1.0.0.4.dist-info/METADATA
odoo_addon_calendar_event_type_color-16.0.1.0.0.4.dist-info/WHEEL
odoo_addon_calendar_event_type_color-16.0.1.0.0.4.dist-info/top_level.txt
odoo_addon_calendar_event_type_color-16.0.1.0.0.4.dist-info/RECORD
